quizmaker3000
