Metadata-Version: 2.1
Name: quizmaker3000
Version: 0.0.1
Summary: A very simple quiz maker. Thats it.. Stop..  It took a while don't question me
Home-page: UNKNOWN
Author: Limeed
Author-email: limeed.yt@gmail.com
License: MIT
Keywords: ASCII,terminal,output
Platform: UNKNOWN
Classifier: Development Status :: 5 - Production/Stable
Classifier: Intended Audience :: Education
Classifier: Operating System :: Microsoft :: Windows :: Windows 10
Classifier: License :: OSI Approved :: MIT License
Classifier: Programming Language :: Python :: 3
License-File: LICENCE.txt
